MANIFEST.in
README.rst
RELEASE
install.sh
setup.py
bin/wBedToWig.py
bin/wSam2Bed.py
bin/wSamToWig.py
bin/wWigPlot.py
bin/wXLSToTXT.py
external/KentLib/README
external/KentLib/makefile
external/KentLib/inc/ace.h
external/KentLib/inc/aliType.h
external/KentLib/inc/apacheLog.h
external/KentLib/inc/asParse.h
external/KentLib/inc/axt.h
external/KentLib/inc/bPlusTree.h
external/KentLib/inc/bamFile.h
external/KentLib/inc/bandExt.h
external/KentLib/inc/base64.h
external/KentLib/inc/basicBed.h
external/KentLib/inc/bbiFile.h
external/KentLib/inc/bigBed.h
external/KentLib/inc/bigWig.h
external/KentLib/inc/binRange.h
external/KentLib/inc/bits.h
external/KentLib/inc/blastParse.h
external/KentLib/inc/boxClump.h
external/KentLib/inc/boxLump.h
external/KentLib/inc/bwgInternal.h
external/KentLib/inc/cda.h
external/KentLib/inc/cgi_build_rules.mk
external/KentLib/inc/chain.h
external/KentLib/inc/chainBlock.h
external/KentLib/inc/chainConnect.h
external/KentLib/inc/chainToAxt.h
external/KentLib/inc/chainToPsl.h
external/KentLib/inc/cheapcgi.h
external/KentLib/inc/cirTree.h
external/KentLib/inc/codebias.h
external/KentLib/inc/colHash.h
external/KentLib/inc/common.h
external/KentLib/inc/common.mk
external/KentLib/inc/correlate.h
external/KentLib/inc/crTree.h
external/KentLib/inc/crudeali.h
external/KentLib/inc/diGraph.h
external/KentLib/inc/diGraph.h.97
external/KentLib/inc/dlist.h
external/KentLib/inc/dnaLoad.h
external/KentLib/inc/dnaMarkov.h
external/KentLib/inc/dnaMotif.h
external/KentLib/inc/dnaseq.h
external/KentLib/inc/dnautil.h
external/KentLib/inc/dtdParse.h
external/KentLib/inc/dystring.h
external/KentLib/inc/emblParse.h
external/KentLib/inc/ens.h
external/KentLib/inc/errCatch.h
external/KentLib/inc/errabort.h
external/KentLib/inc/fa.h
external/KentLib/inc/filePath.h
external/KentLib/inc/flydna.h
external/KentLib/inc/fof.h
external/KentLib/inc/fuzzyFind.h
external/KentLib/inc/gapCalc.h
external/KentLib/inc/gdf.h
external/KentLib/inc/genoFind.h
ngslib.egg-info/PKG-INFO
ngslib.egg-info/SOURCES.txt
ngslib.egg-info/dependency_links.txt
ngslib.egg-info/requires.txt
ngslib.egg-info/top_level.txt
