Metadata-Version: 1.1
Name: ngslib
Version: 1.1.19
Summary: Python Modules for Next-Generation Sequencing Data Analysis.
Home-page: http://tsznxx.appspot.com
Author: Yunfei Wang
Author-email: yfwang0405@gmail.com
License: GNU General Public License (GPL)
Keywords: Python Sequencing Bed BigWig TwoBit
Platform: UNKNOWN
Classifier: Environment :: Console
Classifier: Development Status :: 3 - Alpha
Classifier: Intended Audience :: Developers
Classifier: License :: OSI Approved :: GNU General Public License (GPL)
Classifier: License :: Free for non-commercial use
Classifier: Operating System :: Unix
Classifier: Programming Language :: Python :: 2.7
Classifier: Topic :: Scientific/Engineering :: Bio-Informatics
